LICENSE
README.md
pyproject.toml
setup.py
src/SuperIntervals.hpp
src/superintervals.hpp
src/superintervals/__init__.py
src/superintervals/intervalmap.cpp
src/superintervals/intervalmap.pxd
src/superintervals/intervalmap.pyx
src/superintervals.egg-info/PKG-INFO
src/superintervals.egg-info/SOURCES.txt
src/superintervals.egg-info/dependency_links.txt
src/superintervals.egg-info/requires.txt
src/superintervals.egg-info/top_level.txt