Metadata-Version: 2.1
Name: superintervals
Version: 0.3.2
Summary: Rapid interval intersections
Author: Kez Cleal
Author-email: Kez Cleal <clealk@cardiff.ac.uk>
License-File: LICENSE
Requires-Dist: Cython
